README.md
setup.py
rodin_helpers/__init__.py
rodin_helpers.egg-info/PKG-INFO
rodin_helpers.egg-info/SOURCES.txt
rodin_helpers.egg-info/dependency_links.txt
rodin_helpers.egg-info/not-zip-safe
rodin_helpers.egg-info/requires.txt
rodin_helpers.egg-info/top_level.txt
rodin_helpers/ch/__init__.py
rodin_helpers/ch/ch.py