Metadata-Version: 2.1
Name: rodin-helpers
Version: 0.1.1
Summary: Collection of python helpers to prettier print
Home-page: https://github.com/madiedinro/rodin_helpers_py
Author: Dmitry Rodin
Author-email: madiedinro@gmail.com
License: MIT
Project-URL: Homepage, https://github.com/madiedinro/rodin_helpers_py
Platform: UNKNOWN
Classifier: Development Status :: 3 - Alpha
Classifier: License :: OSI Approved :: MIT License
Classifier: Programming Language :: Python :: 3.6
Classifier: Programming Language :: Python :: 3.7
